setup.cfg
setup.py
bin/datums
datums/__init__.py
datums.egg-info/PKG-INFO
datums.egg-info/SOURCES.txt
datums.egg-info/dependency_links.txt
datums.egg-info/pbr.json
datums.egg-info/requires.txt
datums.egg-info/top_level.txt
datums/models/__init__.py
datums/models/base.py
datums/models/questions.py
datums/models/responses.py
datums/models/snapshots.py
datums/pipeline/__init__.py
datums/pipeline/add.py
datums/pipeline/codec.py
datums/pipeline/delete.py
datums/pipeline/update.py