Metadata-Version: 1.1
Name: datums
Version: 0.0.5
Summary: A PostgreSQL pipeline for Reporter.
Home-page: https://github.com/thejunglejane/datums
Author: Jane Stewart Adams
Author-email: jane@thejunglejane.com
License: MIT
Download-URL: https://github.com/thejunglejane/datums/tarball/0.0.5
Platform: UNKNOWN
